README.md
setup.cfg
setup.py
iot_rdb/__init__.py
iot_rdb/util.py
iot_rdb.egg-info/PKG-INFO
iot_rdb.egg-info/SOURCES.txt
iot_rdb.egg-info/dependency_links.txt
iot_rdb.egg-info/requires.txt
iot_rdb.egg-info/top_level.txt