Metadata-Version: 2.1
Name: iot-rdb
Version: 0.2.1
Summary: Redis iot implementation for conecting containers in Jetson Xavier NX
Home-page: https://github.com/OF306PUC/iot-plc-project/tree/main/tools/packages/iot-rdb
Author: Francisco Fonseca
Author-email: fffonseca@uc.cl
Requires-Python: >=3.6
